AUTHORS
LICENSE
MANIFEST.in
README
Vagrantfile
conftest.py
dev-requirements.txt
setup.py
tasks.py
tox.ini
syskit/__init__.py
syskit/_apipkg.py
syskit/_enum34.py
syskit/_errors.py
syskit/_host.py
syskit/_host_aix.py
syskit/_host_linux.py
syskit/_host_sunos.py
syskit/_process.py
syskit/_process_aix.py
syskit/_process_linux.py
syskit/_process_sunos.py
syskit/_six.py
syskit/_timespec.py
syskit/_utils.py
syskit/sargs64.c
syskit.egg-info/PKG-INFO
syskit.egg-info/SOURCES.txt
syskit.egg-info/dependency_links.txt
syskit.egg-info/not-zip-safe
syskit.egg-info/requires.txt
syskit.egg-info/top_level.txt
syskit/_bindings/__init__.py
syskit/_bindings/ffi_aix_perfstat.py
syskit/_bindings/ffi_aix_process.py
syskit/_bindings/ffi_sunos_process.py
syskit/_bindings/ffi_utmpx.py
tests/conftest.py
tests/test_host.py
tests/test_host_impl.py
tests/test_process.py
tests/test_process_impl.py
tests/test_syskit.py
tests/test_timespec.py