Metadata-Version: 1.1
Name: syskit
Version: 0.2.1
Summary: System information for pedants
Home-page: http://hg.sr.ht/~flub/syskit
Author: Floris Bruynooghe
Author-email: flub@devork.be
License: MIT
Download-URL: http://pypi.python.org/pypi/syskit
Platform: UNKNOWN
Classifier: Development Status :: 2 - Pre-Alpha
Classifier: License :: OSI Approved :: MIT License
Classifier: Intended Audience :: Developers
Classifier: Operating System :: POSIX :: Linux
Classifier: Operating System :: POSIX :: SunOS/Solaris
Classifier: Programming Language :: C
Classifier: Programming Language :: Python
Classifier: Programming Language :: Python :: 2
Classifier: Programming Language :: Python :: 3
Classifier: Topic :: Software Development :: Libraries :: Python Modules
Classifier: Topic :: System :: Operating System Kernels
Classifier: Topic :: System :: Systems Administration
